zeroentropy/__init__.py
zeroentropy/_base_client.py
zeroentropy/_client.py
zeroentropy/_compat.py
zeroentropy/_constants.py
zeroentropy/_exceptions.py
zeroentropy/_files.py
zeroentropy/_models.py
zeroentropy/_qs.py
zeroentropy/_resource.py
zeroentropy/_response.py
zeroentropy/_streaming.py
zeroentropy/_types.py
zeroentropy/_version.py
zeroentropy/pagination.py
zeroentropy/py.typed
zeroentropy/_utils/__init__.py
zeroentropy/_utils/_compat.py
zeroentropy/_utils/_datetime_parse.py
zeroentropy/_utils/_logs.py
zeroentropy/_utils/_proxy.py
zeroentropy/_utils/_reflection.py
zeroentropy/_utils/_resources_proxy.py
zeroentropy/_utils/_streams.py
zeroentropy/_utils/_sync.py
zeroentropy/_utils/_transform.py
zeroentropy/_utils/_typing.py
zeroentropy/_utils/_utils.py
zeroentropy/lib/.keep
zeroentropy/resources/__init__.py
zeroentropy/resources/collections.py
zeroentropy/resources/documents.py
zeroentropy/resources/models.py
zeroentropy/resources/queries.py
zeroentropy/resources/status.py
zeroentropy/types/__init__.py
zeroentropy/types/collection_add_params.py
zeroentropy/types/collection_add_response.py
zeroentropy/types/collection_delete_params.py
zeroentropy/types/collection_delete_response.py
zeroentropy/types/collection_get_list_response.py
zeroentropy/types/document_add_params.py
zeroentropy/types/document_add_response.py
zeroentropy/types/document_delete_params.py
zeroentropy/types/document_delete_response.py
zeroentropy/types/document_get_info_list_params.py
zeroentropy/types/document_get_info_list_response.py
zeroentropy/types/document_get_info_params.py
zeroentropy/types/document_get_info_response.py
zeroentropy/types/document_get_page_info_params.py
zeroentropy/types/document_get_page_info_response.py
zeroentropy/types/document_update_params.py
zeroentropy/types/document_update_response.py
zeroentropy/types/model_rerank_params.py
zeroentropy/types/model_rerank_response.py
zeroentropy/types/query_top_documents_params.py
zeroentropy/types/query_top_documents_response.py
zeroentropy-0.1.0a8.dist-info/METADATA
zeroentropy-0.1.0a8.dist-info/WHEEL
zeroentropy-0.1.0a8.dist-info/licenses/LICENSE
zeroentropy-0.1.0a8.dist-info/RECORD
